src/global_numerics.v
/*******************************************************************
*
* Module: global_numerics.v
* Project: Serial_Parallel_Multiplier
* Author: Ahmed Refaay - refaay@aucegypt.edu
* Description: global numeric values declaration file to be included in project modules
*
* Change history: 02/15/18 – Finished module
*
**********************************************************************/

`timescale 1ns/1ns
`default_nettype none

src/I2C_Master.v
/*******************************************************************
*
* Module: I2C_Master.v
* Project: I2C Master
* Author: Ahmed Refaay - refaay@aucegypt.edu
* Description: I2C Master full circuit
*
* Change history: 02/21/18 – Created module
*                 02/23/18 – Finished module
*
**********************************************************************/

`include "src/global_numerics.v"

module I2C_Master(clk, rst, En, RW, ADDR, DataIn, DataOut, SCL, iSDA, oSDA);
    input wire [0:0] clk; // global clock
    input wire [0:0] rst; // global reset
    
    input wire [0:0] En; // The master responds to R/W if and only if En is 1
    input wire [0:0] RW; // Read (1)/Write (0) control
    input wire [1:0] ADDR; // input address for register manipulation
    input wire [7:0] DataIn; // input data
    output reg [7:0] DataOut; // output data

    output wire [0:0] SCL; // the I2C clock signal for the slaves
	//inout SDA; // inout data signal for slaves -> didn't work on CloudV
    
	input wire [0:0] iSDA; // the I2C data input signal from the slaves
    output reg [0:0] oSDA; // the I2C data output signal for the slaves
    reg [6:0] AU; // address 00: AU register (write only); 8 bits
    reg [7:0] DU; // address 01: DU register (write only); 8 bits
    reg [0:0] GO; // address 10: GO (write only); 1 bit
    reg [1:0] STATUS; // address 11: STATUS (read only); 2 bits; bit 0: done, bit 1: success
    
    reg [4:0] counter; // to count up to 8 cycles

    assign SCL = ((counter >= 5'd20) || (counter <= 5'd1))? 1'b1 :  !clk;
    //assign SDA = ((counter == 5'd10) || (counter == 5'd19))? 1'bz : oSDA;
	//assign iSDA = ((counter == 5'd10) || (counter == 5'd19))? SDA : 1'bz;
    
    always @(posedge clk or negedge rst) begin
        if (!rst) begin
            AU <= 7'd0;
            DU <= 8'd0;
            GO <= 1'd0;
            STATUS <= 2'd0;
            DataOut <= 8'd0;
            counter <= 5'd0;
            oSDA <= 1'd1;
        end
        else begin
            if(En == 1'b1) begin
                STATUS <= STATUS;
                counter <= counter;
                oSDA <= 1'd1;
                case(ADDR)
                    2'b00: begin
                        if(RW == 1'b0) AU <= DataIn[6:0];
                        else AU <= AU;
                        DU <= DU;
                        GO <= GO;
                        DataOut <= DataOut;
                    end
                    2'b01: begin
                        AU <= AU;
                        if(RW == 1'b0) DU <= DataIn;
                        else DU <= DU;
                        GO <= GO;
                        DataOut <= DataOut;
                    end
                    2'b10: begin
                        AU <= AU;
                        DU <= DU;
                        if(RW == 1'b0) GO <= DataIn[0];
                        else GO <= GO;
                        DataOut <= DataOut;
                    end
                    default: begin
                        AU <= AU;
                        DU <= DU;
                        GO <= GO;
                        if(RW == 1'b1) DataOut <= {6'd0, STATUS};
                        else DataOut <= DataOut;
                    end
                endcase
            end
            else begin
                AU <= AU;
                DU <= DU;
                DataOut <= DataOut;
                GO <= 1'd0;
                if(GO == 1'b1)begin
                    counter <= 5'd1;
                    STATUS <= 2'd0;
                    oSDA <= 1'd0;
                end
                else begin
                    if(counter == 5'd0) begin // if not enabled or no GO yet, keep everything as it is
                        counter <= counter;
                        STATUS <= 2'd0;
                        oSDA <= 1'd1;
                    end
                    else if(counter <= 5'd7) begin // sending 7-bit address
                        counter <= counter + 5'd1;
                        STATUS <= 2'd0;
                        oSDA <= AU[5'd6-(counter-5'd1)];
                    end
                    else if(counter == 5'd8) begin // sending R/W
                        counter <= counter + 5'd1;
                        STATUS <= 2'd0;
                        oSDA <= 1'd0; // since we only write in this module
                    end
                    else if(counter == 5'd9) begin // receiving acknowledgement
                        counter <= counter + 5'd1;
                        STATUS <= {iSDA, 1'd0}; // acknowledgement is a part of success
                        oSDA <= 1'd0; // output not used
                    end
                    else if(counter <= 5'd17) begin // sending 8-bit data
                        counter <= counter + 5'd1;
                        STATUS <= STATUS;
                        oSDA <= DU[5'd6-(counter-5'd11)];
                    end
                    else if(counter == 5'd18) begin // receiving acknowledgement
                        counter <= counter + 5'd1;
                        STATUS <= {(iSDA & STATUS[1]), 1'd0}; // all acknowledgements make success
                        oSDA <= 1'd0; // output not used
                    end
                    else if(counter == 5'd19) begin // STOP
                        counter <= counter + 5'd1;
                        STATUS <= {STATUS[1], 1'd1}; // sending done
                        oSDA <= 1'd1;
                    end
                    else begin // default
                        counter <= counter;
                        STATUS <= STATUS;
                        oSDA <= 1'd1;
                    end
                end
            end
        end
    end
endmodule

src/I2C_Master_tb.v
// file: I2C_Master_tb.v
// author: @refaay
// Testbench for I2C_Master

`timescale 1ns/1ns

module I2C_Master_tb;

	//Inputs
	reg [0: 0] clk;
	reg [0: 0] rst;
	reg [0: 0] En;
	reg [0: 0] RW;
	reg [1: 0] ADDR;
	reg [7: 0] DataIn;
	reg [0: 0] iSDA;

	//Outputs
	wire [7: 0] DataOut;
	wire [0:0] SCL;
	wire [0: 0] oSDA;

    //Testbench
    reg [16:0] mem;
    reg err;
    reg [6:0] AU; // address
    reg [7:0] DU; // data
    
	//Instantiation of Unit Under Test
	I2C_Master uut (
		.clk(clk),
		.rst(rst),
		.En(En),
		.RW(RW),
		.ADDR(ADDR),
		.DataIn(DataIn),
		.iSDA(iSDA),
		.DataOut(DataOut),
		.SCL(SCL),
		.oSDA(oSDA)
	);

    always #5 clk = !clk;

	initial begin
	//Inputs initialization
		clk = 0;
		rst = 0;
		En = 0;
		RW = 0;
		ADDR = 0;
		DataIn = 0;
		iSDA = 0;
		mem = 0;
		err = 0;
		AU = $random % 7'd100; // address
		DU = $random % 7'd100; // data
		
		#10; //send address
		rst = 1;
		En = 1;
		RW = 0;
		DataIn = AU;
		
		#10; // send data
		ADDR = 1;
		DataIn = DU;
		
		#10; // send GO
		ADDR = 2;
		DataIn = 1;
		
		#10; // let it work
		ADDR = 2;
		DataIn = 0;
		En = 0;
		
		#50; // acknowledge all
		iSDA = 1;
		
        #200; // read STATUS
        ADDR = 3;
        En = 1;
        RW = 1;
        
        #10; // stop reading
        En = 0;
	end
    
    initial begin // store all sent bits and compare to original
        repeat (18) begin
            @(negedge SCL)
            mem = {mem[15:0], oSDA};
        end
        err = mem != {AU, 2'd0, DU};
    end
    
endmodule

build (read-only)/I2C_Master_tb.vcd
$date
	Fri Feb 23 20:35:23 2018
$end
$version
	Icarus Verilog
$end
$timescale
	1ns
$end
$scope module I2C_Master_tb $end
$var wire 1 ! oSDA $end
$var wire 1 " SCL $end
$var wire 8 # DataOut [7:0] $end
$var reg 2 $ ADDR [1:0] $end
$var reg 7 % AU [6:0] $end
$var reg 8 & DU [7:0] $end
$var reg 8 ' DataIn [7:0] $end
$var reg 1 ( En $end
$var reg 1 ) RW $end
$var reg 1 * clk $end
$var reg 1 + err $end
$var reg 1 , iSDA $end
$var reg 17 - mem [16:0] $end
$var reg 1 . rst $end
$scope module uut $end
$var wire 2 / ADDR [1:0] $end
$var wire 8 0 DataIn [7:0] $end
$var wire 1 ( En $end
$var wire 1 ) RW $end
$var wire 1 * clk $end
$var wire 1 , iSDA $end
$var wire 1 . rst $end
$var wire 1 " SCL $end
$var reg 7 1 AU [6:0] $end
$var reg 8 2 DU [7:0] $end
$var reg 8 3 DataOut [7:0] $end
$var reg 1 4 GO $end
$var reg 2 5 STATUS [1:0] $end
$var reg 5 6 counter [4:0] $end
$var reg 1 ! oSDA $end
$upscope $end
$upscope $end
$enddefinitions $end
#0
$dumpvars
b0 6
b0 5
04
b0 3
b0 2
b0 1
b0 0
b0 /
0.
b0 -
0,
0+
0*
0)
0(
b0 '
b1100001 &
b110000 %
b0 $
b0 #
1"
1!
$end
#5
1*
#10
0*
b110000 '
b110000 0
1(
1.
#15
b110000 1
1*
#20
0*
b1100001 '
b1100001 0
b1 $
b1 /
#25
b1100001 2
1*
#30
0*
b1 '
b1 0
b10 $
b10 /
#35
14
1*
#40
0*
0(
b0 '
b0 0
#45
0!
b1 6
04
1*
#50
0*
#55
0"
b10 6
1*
#60
1"
0*
#65
1!
b11 6
0"
1*
#70
1"
0*
#75
b100 6
b1 -
0"
1*
#80
1"
0*
#85
0!
b101 6
b11 -
0"
1*
#90
1"
0*
1,
#95
b110 6
b110 -
0"
1*
#100
1"
0*
#105
b111 6
b1100 -
0"
1*
#110
1"
0*
#115
b1000 6
b11000 -
0"
1*
#120
1"
0*
#125
b1001 6
b110000 -
0"
1*
#130
1"
0*
#135
b10 5
b1010 6
b1100000 -
0"
1*
#140
1"
0*
#145
b1011 6
b11000000 -
0"
1*
#150
1"
0*
#155
1!
b1100 6
b110000000 -
0"
1*
#160
1"
0*
#165
b1101 6
b1100000001 -
0"
1*
#170
1"
0*
#175
0!
b1110 6
b11000000011 -
0"
1*
#180
1"
0*
#185
b1111 6
b110000000110 -
0"
1*
#190
1"
0*
#195
b10000 6
b1100000001100 -
0"
1*
#200
1"
0*
#205
b10001 6
b11000000011000 -
0"
1*
#210
1"
0*
#215
1!
b10010 6
b110000000110000 -
0"
1*
#220
1"
0*
#225
0!
b10011 6
b1100000001100001 -
0"
1*
#230
1"
0*
#235
1!
b11 5
b10100 6
1"
1*
#240
0*
#245
1*
#250
0*
#255
1*
#260
0*
#265
1*
#270
0*
#275
1*
#280
0*
#285
1*
#290
0*
1)
1(
b11 $
b11 /
#295
b11 #
b11 3
1*
#300
0*
0(
